gpColor/__init__.py
gpColor/color.py
gpColor-1.0.1.dist-info/METADATA
gpColor-1.0.1.dist-info/WHEEL
gpColor-1.0.1.dist-info/top_level.txt
gpColor-1.0.1.dist-info/RECORD
