Metadata-Version: 2.1
Name: gpColor
Version: 1.0.1
Summary: A Python module to apply ANSI, RGB and HEX colors in terminal output.
Home-page: https://github.com/gpbot-org/gpColor
Author: Grandpa EJ
License: MIT
Classifier: Programming Language :: Python :: 3
Classifier: License :: OSI Approved :: MIT License
Classifier: Operating System :: OS Independent
Requires-Python: >=3.6
